quizdown-0.3.2.dist-info/METADATA
quizdown-0.3.2.dist-info/WHEEL
quizdown/__main__.py
quizdown/types.py
quizdown/qti_format.py
quizdown/__init__.py
quizdown/templates/qti-quiz.j2
quizdown/templates/qti-quiz-meta.j2
quizdown/templates/__init__.py
quizdown/templates/qti-manifest.j2
quizdown/quizdown.abi3.so
quizdown-0.3.2.dist-info/RECORD
