Metadata-Version: 2.1
Name: quizdown
Version: 0.3.2
Classifier: Programming Language :: Python :: 3.6
Classifier: Operating System :: OS Independent
Requires-Dist: attrs
Requires-Dist: jinja2
Summary: A markdown subset for quickly making multiple-choice questions.
Home-Page: https://github.com/jjfiv/quizdown
Author: John Foley <johnf@middlebury.edu>
Author-email: John Foley <johnf@middlebury.edu>
